functions_by_dinara93/README.md
functions_by_dinara93/math_functions.py
functions_by_dinara93-0.2.0.dist-info/WHEEL
functions_by_dinara93-0.2.0.dist-info/METADATA
functions_by_dinara93-0.2.0.dist-info/RECORD
