Metadata-Version: 2.1
Name: functions-by-dinara93
Version: 0.2.0
Summary: This is our test project
Author: Dinara Aidarova
Author-email: fordinara93@gmail.com
Requires-Python: >=3.10,<4.0
Classifier: Programming Language :: Python :: 3
Classifier: Programming Language :: Python :: 3.10
Classifier: Programming Language :: Python :: 3.11
